sphinx_rtd_dark_mode/__init__.py
sphinx_rtd_dark_mode/dark_mode_loader.py
sphinx_rtd_dark_mode/static/dark_mode_css/custom.css
sphinx_rtd_dark_mode/static/dark_mode_css/dark.css
sphinx_rtd_dark_mode/static/dark_mode_css/general.css
sphinx_rtd_dark_mode/static/dark_mode_js/default_dark.js
sphinx_rtd_dark_mode/static/dark_mode_js/default_light.js
sphinx_rtd_dark_mode/static/dark_mode_js/theme_switcher.js
tests/__init__.py
tests/build.py
sphinx_rtd_dark_mode-1.3.0.dist-info/LICENSE
sphinx_rtd_dark_mode-1.3.0.dist-info/METADATA
sphinx_rtd_dark_mode-1.3.0.dist-info/WHEEL
sphinx_rtd_dark_mode-1.3.0.dist-info/top_level.txt
sphinx_rtd_dark_mode-1.3.0.dist-info/RECORD
