Metadata-Version: 2.1
Name: sphinx-rtd-dark-mode
Version: 1.3.0
Summary: Dark mode for the Sphinx Read the Docs theme.
Home-page: https://github.com/MrDogeBro/sphinx_rtd_dark_mode
Download-URL: https://github.com/MrDogeBro/sphinx_rtd_dark_mode/archive/v1.3.0.tar.gz
Author: MrDogeBro
License: MIT
Classifier: Development Status :: 5 - Production/Stable
Classifier: Framework :: Sphinx :: Extension
Classifier: Natural Language :: English
Classifier: Programming Language :: Python :: 3.5
Classifier: Programming Language :: Python :: 3.6
Classifier: Programming Language :: Python :: 3.7
Classifier: Programming Language :: Python :: 3.8
Classifier: Programming Language :: Python :: 3.9
Classifier: License :: OSI Approved :: MIT License
Classifier: Operating System :: OS Independent
Requires-Python: >=3.4
License-File: LICENSE
Requires-Dist: sphinx-rtd-theme
